LICENSE
README.md
setup.cfg
setup.py
webzip/__init__.py
webzip/installer.py
webzip.egg-info/PKG-INFO
webzip.egg-info/SOURCES.txt
webzip.egg-info/dependency_links.txt
webzip.egg-info/entry_points.txt
webzip.egg-info/requires.txt
webzip.egg-info/top_level.txt