Metadata-Version: 2.1
Name: webzip
Version: 1.0
Summary: Install python packages from any source on the web
Home-page: UNKNOWN
Author: Maximilian Lange
Author-email: maxhlange@gmail.com
License: UNKNOWN
Platform: UNKNOWN
Classifier: License :: OSI Approved :: MIT License
Classifier: Programming Language :: Python :: 3
License-File: LICENSE
